<Ui xmlns="http://www.blizzard.com/wow/ui/" xmlns:xsi="http://www.w3.org/2001/XMLSchema-instance" xsi:schemaLocation="http://www.blizzard.com/wow/ui/
..\FrameXML\UI.xsd">
	<Script file="GearStatsSummary.lua"/>

	<Frame name="GearStatsSummaryFrame" hidden="false" parent="UIParent">
		<Scripts>
			<OnLoad>
				GearStatsSummary_OnLoad(self)
			</OnLoad>
			<OnEvent>
				GearStatsSummary_OnEvent(self, event, ...);
			</OnEvent>
		</Scripts>
	</Frame>

    <Frame name="GearStatsSummarySelfFrame" frameStrata="MEDIUM" toplevel="true" enableMouse="true" movable="true" hidden="true"  parent="UIParent">
		<TitleRegion setAllPoints="true"/>
		<Backdrop bgFile="Interface\DialogFrame\UI-DialogBox-Background" edgeFile="Interface\Tooltips\UI-Tooltip-Border" tile="true">
			<EdgeSize>
				<AbsValue val="8"/>
			</EdgeSize>
			<TileSize>
				<AbsValue val="8"/>
			</TileSize>
			<BackgroundInsets>
				<AbsInset left="2" right="2" top="2" bottom="2"/>
			</BackgroundInsets>
		</Backdrop>
        <Layers>
            <Layer level="BACKGROUND">
                <FontString name="GearStatsSummarySelfFrameTitle" inherits="GameTooltipHeaderText">
                    <Anchors>
                        <Anchor point="TOPLEFT" relativeTo="GearStatsSummarySelfFrame" relativePoint="TOPLEFT">
                            <Offset>
                                <AbsDimension x="10" y="-10"/>
                            </Offset>
                        </Anchor>
                    </Anchors>
                </FontString>
                <FontString name="GearStatsSummarySelfFrameText" inherits="GameTooltipText">
                    <Anchors>
                        <Anchor point="BOTTOMLEFT" relativeTo="GearStatsSummarySelfFrame" relativePoint="BOTTOMLEFT">
                            <Offset>
                                <AbsDimension x="5" y="10"/>
                            </Offset>
                        </Anchor>
                    </Anchors>
                </FontString>
			</Layer>
        </Layers>
        <Frames>
            <Button name="GearStatsSummarySelfFrameCloseButton" inherits="UIPanelCloseButton">
                <Anchors>
                    <Anchor point="TOPRIGHT" relativeTo="GearStatsSummarySelfFrame" relativePoint="TOPRIGHT">
                        <Offset>
                            <AbsDimension x="3" y="3"/>
                        </Offset>
                    </Anchor>
                </Anchors>
            </Button>
        </Frames>
    </Frame>

    <Frame name="GearStatsSummaryTargetFrame" frameStrata="MEDIUM" toplevel="true" enableMouse="true" movable="true" hidden="true"  parent="UIParent">
		<TitleRegion setAllPoints="true"/>
		<Backdrop bgFile="Interface\DialogFrame\UI-DialogBox-Background" edgeFile="Interface\Tooltips\UI-Tooltip-Border" tile="true">
			<EdgeSize>
				<AbsValue val="8"/>
			</EdgeSize>
			<TileSize>
				<AbsValue val="8"/>
			</TileSize>
			<BackgroundInsets>
				<AbsInset left="2" right="2" top="2" bottom="2"/>
			</BackgroundInsets>
		</Backdrop>
        <Layers>
            <Layer level="BACKGROUND">
                <FontString name="GearStatsSummaryTargetFrameTitle" inherits="GameTooltipHeaderText">
                    <Anchors>
                        <Anchor point="TOPLEFT" relativeTo="GearStatsSummaryTargetFrame" relativePoint="TOPLEFT">
                            <Offset>
                                <AbsDimension x="10" y="-10"/>
                            </Offset>
                        </Anchor>
                    </Anchors>
                </FontString>
                <FontString name="GearStatsSummaryTargetFrameText" inherits="GameTooltipText">
                    <Anchors>
                        <Anchor point="BOTTOMLEFT" relativeTo="GearStatsSummaryTargetFrame" relativePoint="BOTTOMLEFT">
                            <Offset>
                                <AbsDimension x="5" y="10"/>
                            </Offset>
                        </Anchor>
                    </Anchors>
                </FontString>
			</Layer>
        </Layers>
        <Frames>
            <Button name="GearStatsSummaryTargetFrameCloseButton" inherits="UIPanelCloseButton">
                <Anchors>
                    <Anchor point="TOPRIGHT" relativeTo="GearStatsSummaryTargetFrame" relativePoint="TOPRIGHT">
                        <Offset>
                            <AbsDimension x="3" y="3"/>
                        </Offset>
                    </Anchor>
                </Anchors>
            </Button>
        </Frames>
		<Scripts>
			<OnHide>
				GearStatsSummarySelfFrame:Hide();
			</OnHide>
		</Scripts>
    </Frame>


</Ui>